pymeianlike/__init__.py
pymeianlike/pymeianlike.py
pymeianlike-1.0.0.dist-info/LICENSE.md
pymeianlike-1.0.0.dist-info/METADATA
pymeianlike-1.0.0.dist-info/WHEEL
pymeianlike-1.0.0.dist-info/top_level.txt
pymeianlike-1.0.0.dist-info/RECORD
